censusname/__init__.py
censusname/__main__.py
censusname/censusname.py
censusname/formatters.py
censusname/__pycache__/__init__.cpython-34.pyc
censusname/__pycache__/censusname.cpython-34.pyc
censusname/__pycache__/formatters.cpython-34.pyc
censusname/data/dist.all.last.1990.csv
censusname/data/dist.all.last.2000.csv
censusname/data/dist.female.first.1990.csv
censusname/data/dist.male.first.1990.csv
censusname-0.2.2.dist-info/DESCRIPTION.rst
censusname-0.2.2.dist-info/METADATA
censusname-0.2.2.dist-info/RECORD
censusname-0.2.2.dist-info/WHEEL
censusname-0.2.2.dist-info/metadata.json
censusname-0.2.2.dist-info/top_level.txt
censusname-0.2.2.dist-info/zip-safe
censusname.egg-info/PKG-INFO
censusname.egg-info/SOURCES.txt
censusname.egg-info/dependency_links.txt
censusname.egg-info/entry_points.txt
censusname.egg-info/top_level.txt
censusname.egg-info/zip-safe
