Metadata-Version: 2.0
Name: censusname
Version: 0.2.2
Summary: Generate random names
Home-page: https://github.com/fitnr/censusname
Author: Neil Freeman
Author-email: contact@fakeisthenewreal.org
License: GPL
Keywords: names development random
Platform: UNKNOWN
Classifier: Development Status :: 4 - Beta
Classifier: Intended Audience :: Developers
Classifier: License :: OSI Approved :: MIT License
Classifier: Programming Language :: Python :: 2
Classifier: Programming Language :: Python :: 2.7
Classifier: Programming Language :: Python :: 3
